python_scinote/__init__.py
python_scinote/client.py
python_scinote-0.2.8.dist-info/WHEEL
python_scinote-0.2.8.dist-info/METADATA
python_scinote-0.2.8.dist-info/RECORD
